littlelogger/__init__.py
littlelogger/constants.py
littlelogger/decorator.py
littlelogger/exceptions.py
littlelogger/util.py
littlelogger-1.1.1.dist-info/METADATA
littlelogger-1.1.1.dist-info/WHEEL
littlelogger-1.1.1.dist-info/licenses/LICENSE
littlelogger-1.1.1.dist-info/RECORD
