Metadata-Version: 2.4
Name: littlelogger
Version: 1.1.1
Summary: A lightweight, zero-setup decorator for logging ML experiments to a JSONL file.
License-Expression: MIT
License-File: LICENSE
Author: Asif Sayyed
Author-email: asifdotexe@gmail.com
Requires-Python: >=3.10
Classifier: Development Status :: 4 - Beta
Classifier: Intended Audience :: Developers
Classifier: Intended Audience :: Science/Research
Classifier: Topic :: Scientific/Engineering
Classifier: Topic :: Software Development :: Libraries :: Python Modules
Classifier: Topic :: Utilities
Classifier: License :: OSI Approved :: MIT License
Classifier: Operating System :: OS Independent
Classifier: Programming Language :: Python :: 3
Classifier: Programming Language :: Python :: 3.10
Classifier: Programming Language :: Python :: 3.11
Classifier: Programming Language :: Python :: 3.12
Classifier: Programming Language :: Python :: 3.13
Project-URL: Homepage, https://github.com/Asifdotexe/LittleLogger
Project-URL: Issues, https://github.com/Asifdotexe/LittleLogger/issues
